garpix_user/CHANGELOG.md
garpix_user/CONTRIBUTING.md
garpix_user/MANIFEST.in
garpix_user/README.md
garpix_user/README.rst
garpix_user/__init__.py
garpix_user/apps.py
garpix_user/exceptions.py
garpix_user/settings.py
garpix_user/setup.py
garpix_user/urls.py
garpix_user/admin/__init__.py
garpix_user/admin/referral_type.py
garpix_user/admin/user.py
garpix_user/admin/user_session.py
garpix_user/forms/__init__.py
garpix_user/forms/login.py
garpix_user/locale/ru/LC_MESSAGES/django.mo
garpix_user/locale/ru/LC_MESSAGES/django.po
garpix_user/mixins/__init__.py
garpix_user/mixins/models/__init__.py
garpix_user/mixins/models/restore_password.py
garpix_user/mixins/models/confirm/__init__.py
garpix_user/mixins/models/confirm/code_length_mixin.py
garpix_user/mixins/models/confirm/email_confirm.py
garpix_user/mixins/models/confirm/phone_confirm.py
garpix_user/mixins/serializers/__init__.py
garpix_user/mixins/serializers/password_mixin.py
garpix_user/mixins/serializers/to_lower.py
garpix_user/models/__init__.py
garpix_user/models/access_token.py
garpix_user/models/refferal.py
garpix_user/models/refresh_token.py
garpix_user/models/user.py
garpix_user/models/user_session.py
garpix_user/rest/__init__.py
garpix_user/rest/authentication.py
garpix_user/serializers/__init__.py
garpix_user/serializers/auth_token_serializer.py
garpix_user/serializers/email_confirmation_serializer.py
garpix_user/serializers/jwt_data_serializer.py
garpix_user/serializers/passwrod_serializer.py
garpix_user/serializers/phone_confirmation_serializer.py
garpix_user/serializers/refresh_token_serializer.py
garpix_user/serializers/registration_serializer.py
garpix_user/serializers/user_session_serializer.py
garpix_user/tasks/__init__.py
garpix_user/tasks/delete_unconfirmed_users.py
garpix_user/templates/garpix_user/send_confirm.html
garpix_user/tests/__init__.py
garpix_user/tests/test_views.py
garpix_user/tests/test_api/__init__.py
garpix_user/tests/test_api/api_login.py
garpix_user-3.9.1.dist-info/METADATA
garpix_user-3.9.1.dist-info/WHEEL
garpix_user-3.9.1.dist-info/top_level.txt
garpix_user-3.9.1.dist-info/RECORD
