Metadata-Version: 2.1
Name: garpix-user
Version: 3.9.1
Home-page: https://github.com/garpixcms/garpix_user
Author: Garpix LTD
Author-email: info@garpix.com
License: MIT
Classifier: Development Status :: 4 - Beta
Classifier: Environment :: Web Environment
Classifier: Intended Audience :: Developers
Classifier: License :: OSI Approved :: MIT License
Classifier: Operating System :: OS Independent
Classifier: Programming Language :: Python
Classifier: Framework :: Django
Classifier: Programming Language :: Python :: 3.6
Classifier: Programming Language :: Python :: 3.7
Classifier: Programming Language :: Python :: 3.8
Requires-Dist: Django (<4,>=3.1)
Requires-Dist: djangorestframework (>=3.8)
Requires-Dist: django-oauth-toolkit (>=1.1.2)
Requires-Dist: social-auth-app-django (>=2.1.0)
Requires-Dist: social-auth-core (==4.3.0)
Requires-Dist: django-rest-framework-social-oauth2 (>=1.1.0)
Requires-Dist: django-phonenumber-field-for-garpix-user (>=8.0.0)
Requires-Dist: garpix-notify (>=5.12.5)
Requires-Dist: garpix-utils (>=1.5.1)
Requires-Dist: drf-spectacular (>=0.24.2)
